pii_codex/__init__.py
pii_codex/config.py
pii_codex/models/__init__.py
pii_codex/models/analysis.py
pii_codex/models/aws_pii.py
pii_codex/models/azure_pii.py
pii_codex/models/common.py
pii_codex/models/microsoft_presidio_pii.py
pii_codex/services/__init__.py
pii_codex/services/analysis_service.py
pii_codex/services/assessment_service.py
pii_codex/services/pii_type_mappings.py
pii_codex/services/adapters/__init__.py
pii_codex/services/adapters/detection_adapters/__init__.py
pii_codex/services/adapters/detection_adapters/aws_detection_adapter.py
pii_codex/services/adapters/detection_adapters/azure_detection_adapter.py
pii_codex/services/adapters/detection_adapters/detection_adapter_base.py
pii_codex/services/adapters/detection_adapters/presidio_detection_adapter.py
pii_codex/services/analyzers/__init__.py
pii_codex/services/analyzers/presidio_analysis.py
pii_codex/utils/__init__.py
pii_codex/utils/logging.py
pii_codex/utils/package_installer_util.py
pii_codex/utils/pii_mapping_util.py
pii_codex/utils/statistics_util.py
pii_codex-0.5.0.dist-info/METADATA
pii_codex-0.5.0.dist-info/WHEEL
pii_codex-0.5.0.dist-info/licenses/LICENSE
pii_codex-0.5.0.dist-info/RECORD
