Metadata-Version: 2.4
Name: pii-codex
Version: 0.5.0
Summary: PII Detection, Categorization, and Severity Assessment
Project-URL: Homepage, https://github.com/EdyVision/pii-codex
Project-URL: Repository, https://github.com/EdyVision/pii-codex
Author: Eidan J. Rosado
License: BSD 3-Clause
License-File: LICENSE
Keywords: PII,PII topology,personal identifiable information,risk assessment,risk categories
Classifier: Development Status :: 1 - Planning
Classifier: Intended Audience :: Science/Research
Classifier: License :: OSI Approved :: BSD License
Classifier: Programming Language :: Python :: 3
Requires-Python: <3.13,>=3.9
Requires-Dist: dataclasses-json<0.6.0,>=0.5.7
Requires-Dist: pandas<3.0.0,>=2.0.0
Requires-Dist: pdoc<14.0.0,>=13.1.1
Requires-Dist: pillow<11.0.0,>=10.0.0
Requires-Dist: pydantic[dotenv]<2.0.0,>=1.10.2
Provides-Extra: detections
Requires-Dist: presidio-analyzer>=2.2.359; extra == 'detections'
Requires-Dist: presidio-anonymizer>=2.2.359; extra == 'detections'
Requires-Dist: spacy>=3.8.7; extra == 'detections'
Provides-Extra: dev
Requires-Dist: assertpy<2.0.0,>=1.1; extra == 'dev'
Requires-Dist: black<24.0.0,>=23.0.0; extra == 'dev'
Requires-Dist: coverage<8.0.0,>=7.2.0; extra == 'dev'
Requires-Dist: faker<20.0.0,>=19.0.0; extra == 'dev'
Requires-Dist: importlib-resources<7.0.0,>=6.0.0; extra == 'dev'
Requires-Dist: ipykernel<7.0.0,>=6.25.0; extra == 'dev'
Requires-Dist: jupyter-core<6.0.0,>=5.0.0; extra == 'dev'
Requires-Dist: jupyter<2.0.0,>=1.0.0; extra == 'dev'
Requires-Dist: matplotlib<4.0.0,>=3.7.0; extra == 'dev'
Requires-Dist: mypy<2.0.0,>=1.5.0; extra == 'dev'
Requires-Dist: pre-commit<4.0.0,>=3.0.0; extra == 'dev'
Requires-Dist: presidio-analyzer>=2.2.360; extra == 'dev'
Requires-Dist: presidio-anonymizer>=2.2.360; extra == 'dev'
Requires-Dist: pylint<4.0.0,>=3.0.0; extra == 'dev'
Requires-Dist: pytest<8.0.0,>=7.4.0; extra == 'dev'
Requires-Dist: seaborn<1.0.0,>=0.12.0; extra == 'dev'
Requires-Dist: spacy>=3.8.7; extra == 'dev'
Requires-Dist: tomli<3.0.0,>=1.2.0; extra == 'dev'
